addition/__init__.py
addition/addition_by_three.py
divide/__init__.py
divide/divide_by_three.py
multiply/__init__.py
multiply/multiply_by_three.py
subtraction/__init__.py
subtraction/subtraction_by_three.py
first_package_by_shibilicv-1.0.0.dist-info/LICENSE.txt
first_package_by_shibilicv-1.0.0.dist-info/METADATA
first_package_by_shibilicv-1.0.0.dist-info/WHEEL
first_package_by_shibilicv-1.0.0.dist-info/top_level.txt
first_package_by_shibilicv-1.0.0.dist-info/RECORD
