Metadata-Version: 2.1
Name: first_package_by_shibilicv
Version: 1.0.0
Summary: A simple Python package that allows to add, subtract, multiply, and divide by three
Home-page: https://github.com/mohd-shibilicv/first_package_by_shibilicv
Author: Mohammed Shibili cv
Author-email: mohdshibilicv@gmail.com
Project-URL: Bug Tracker, https://github.com/mohd-shibilicv/first_package_by_shibilicv
Project-URL: repository, https://github.com/mohd-shibilicv/first_package_by_shibilicv
Classifier: Programming Language :: Python :: 3
Classifier: License :: OSI Approved :: MIT License
Classifier: Operating System :: OS Independent
Requires-Python: >=3.6
License-File: LICENSE.txt
